setup.cfg
setup.py
DBSync.egg-info/PKG-INFO
DBSync.egg-info/SOURCES.txt
DBSync.egg-info/dependency_links.txt
DBSync.egg-info/not-zip-safe
DBSync.egg-info/requires.txt
DBSync.egg-info/top_level.txt
dbsync/__init__.py
dbsync/manager.py
dbsync/scheduler.py
dbsync/generators/__init__.py
dbsync/generators/peewee.py
dbsync/generators/schema.py
dbsync/models/__init__.py
dbsync/models/base.py
dbsync/models/mongodb.py
dbsync/models/peewee.py
dbsync/models/sqlalchemy.py
dbsync/serializers/__init__.py
dbsync/serializers/avro.py
dbsync/serializers/base.py
dbsync/serializers/csv.py
dbsync/serializers/json.py
dbsync/serializers/pickle.py
dbsync/syncs/__init__.py
dbsync/syncs/base.py
dbsync/syncs/gearman.py
dbsync/syncs/hadoop.py
dbsync/syncs/pool.py
dbsync/syncs/spark.py
dbsync/utils/__init__.py