Metadata-Version: 1.1
Name: DBSync
Version: 0.1.1
Summary: Sync database to hadoop
Home-page: http://github.com/zhoubangtao/dbsync
Author: Bangtao Zhou
Author-email: zhoubangtao@163.com
License: MIT
Keywords: sync hive hadoop mysql mongodb
Platform: UNKNOWN
Classifier: Development Status :: 5 - Production/Stable
Classifier: Intended Audience :: Developers
Classifier: License :: OSI Approved :: MIT License
Classifier: Programming Language :: Python
Classifier: Programming Language :: Python :: 2.6
Classifier: Programming Language :: Python :: 2.7
Classifier: Programming Language :: Python :: 3
Classifier: Programming Language :: Python :: 3.2
Classifier: Programming Language :: Python :: 3.3
Classifier: Programming Language :: Python :: 3.4
